[
	{ "name": { "en": "Kidzo" } },
	{ "name": { "en": "Montaly" } },
	{ "name": { "en": "Mami Baby" } },
	{ "name": { "en": "Winnie Care" } },
	{ "name": { "en": "Little Home" } },
	{ "name": { "en": "Mums World" } },
	{ "name": { "en": "Nannanqin" } },
	{ "name": { "en": "Nexton" } },
	{ "name": { "en": "Pampars" } },
	{ "name": { "en": "Johnson" } },
	{ "name": { "en": "Pigeon" } },
	{ "name": { "en": "Dr. Rasheel" } },
	{ "name": { "en": "Farlin" } },
	{ "name": { "en": "Hercules Bear" } },
	{ "name": { "en": "Flower Baby" } },
	{ "name": { "en": "Only Baby" } },
	{ "name": { "en": "Smart Baby" } },
	{ "name": { "en": "Minitree" } },
	{ "name": { "en": "Maq" } },
	{ "name": { "en": "Liock Baby" } },
	{ "name": { "en": "Yes" } },
	{ "name": { "en": "Fish" } },
	{ "name": { "en": "Preety Baby" } },
	{ "name": { "en": "BnB" } }
]
